needle/__init__.py
needle/_version.py
needle/search.py
needle/stack.py
needle/viewer.py
needle/examples/__init__.py
needle/examples/__main__.py
python_needle-0.1.dev38.dist-info/LICENSE
python_needle-0.1.dev38.dist-info/METADATA
python_needle-0.1.dev38.dist-info/WHEEL
python_needle-0.1.dev38.dist-info/top_level.txt
python_needle-0.1.dev38.dist-info/RECORD
