Metadata-Version: 2.1
Name: python-needle
Version: 0.1.dev38
Summary: A package helping to navigate nested structures easily
Author-email: devforfu <developer.z@outlook.com>
Project-URL: code, https://github.com/devforfu/needle
Classifier: Programming Language :: Python :: 3
Requires-Python: >=3.9
License-File: LICENSE
Requires-Dist: rich
Provides-Extra: test
Requires-Dist: pytest ; extra == 'test'
